Metadata-Version: 2.1
Name: mkdocs-swagger-ui
Version: 0.2.4
Summary: An MkDocs plugin to generate a markdown file containing an API reference built using Swagger UI from a base OAS3 specification.
Home-page: https://github.com/byrnereese/mkdocs-swagger-ui
Author: Byrne Reese
Author-email: byrne@majordojo.com
License: MIT
Keywords: mkdocs swagger api documentation
Classifier: Development Status :: 4 - Beta
Classifier: Intended Audience :: Developers
Classifier: Intended Audience :: Information Technology
Classifier: License :: OSI Approved :: MIT License
Classifier: Programming Language :: Python
Classifier: Programming Language :: Python :: 3 :: Only
Classifier: Programming Language :: Python :: 3.4
Classifier: Programming Language :: Python :: 3.5
Classifier: Programming Language :: Python :: 3.6
Classifier: Programming Language :: Python :: 3.7
Requires-Python: >=3.0
License-File: LICENSE
